NXTfusion/DataMatrix.py
NXTfusion/Logger.py
NXTfusion/NXCollateUtils.py
NXTfusion/NXDatasetUtils.py
NXTfusion/NXFeaturesConstruction.py
NXTfusion/NXLosses.py
NXTfusion/NXMetaLoaderUtils.py
NXTfusion/NXTfusion.py
NXTfusion/NXmodels.py
NXTfusion/NXmultiRelSide.py
NXTfusion/__init__.py
NXTfusion-0.0.5.dist-info/METADATA
NXTfusion-0.0.5.dist-info/WHEEL
NXTfusion-0.0.5.dist-info/top_level.txt
NXTfusion-0.0.5.dist-info/RECORD
