Metadata-Version: 2.1
Name: NXTfusion
Version: 0.0.5
Summary: Non linear data fusion over Entity Relation graphs
Home-page: https://bitbucket.org/eddiewrc/nxtfusion/src/master/
Author: Daniele Raimondi
Author-email: daniele.raimondi@kuleuven.be
License: UNKNOWN
Platform: UNKNOWN
Classifier: Programming Language :: Python :: 3
Classifier: License :: OSI Approved :: GNU General Public License v2 (GPLv2)
Classifier: Operating System :: OS Independent
Requires-Python: >=3.6
Requires-Dist: numpy
Requires-Dist: scipy
Requires-Dist: multipledispatch
Requires-Dist: torch
Requires-Dist: torchvision
